_dvg_pyqt_controls__deprecated.py
dvg_pyqt_controls.py
dvg_pyqt_controls-1.5.0.dist-info/AUTHORS.rst
dvg_pyqt_controls-1.5.0.dist-info/LICENSE.txt
dvg_pyqt_controls-1.5.0.dist-info/METADATA
dvg_pyqt_controls-1.5.0.dist-info/WHEEL
dvg_pyqt_controls-1.5.0.dist-info/top_level.txt
dvg_pyqt_controls-1.5.0.dist-info/RECORD
