Metadata-Version: 2.1
Name: dvg-pyqt-controls
Version: 1.5.0
Summary: Mishmash of PyQt/PySide stylesheets and custom controls that I personally use in many of my projects.
Home-page: https://github.com/Dennis-van-Gils/python-dvg-pyqt-controls
Author: Dennis van Gils
Author-email: vangils.dennis@gmail.com
License: MIT
Project-URL: Issue Tracker, https://github.com/Dennis-van-Gils/python-dvg-pyqt-controls/issues
Keywords: PyQt5,PyQt6,PySide2,PySide6,controls,stylesheets
Classifier: Development Status :: 5 - Production/Stable
Classifier: License :: OSI Approved :: MIT License
Classifier: Intended Audience :: Developers
Classifier: Intended Audience :: Science/Research
Classifier: Operating System :: OS Independent
Classifier: Programming Language :: Python
Classifier: Programming Language :: Python :: 3
Classifier: Topic :: Utilities
Classifier: Topic :: Scientific/Engineering 
Classifier: Topic :: Scientific/Engineering :: Electronic Design Automation (EDA)
Requires-Python: >=3.6
License-File: LICENSE.txt
License-File: AUTHORS.rst
